crc32_parallel_pipeline.sv
/* Michael Mostytskyy
 Project: CRC32 Ethernet Accelerator
 Description: 
    Hardware implementation of a parallel CRC32 engine (IEEE 802.3)
    It processes 32 bits per cycle using a pipeline stage for high speed
*/

module CRC32_parallel_pipeline (
    input  logic        clk,
    input  logic        reset_n,
    input  logic        enable,          // Tells us when data is valid
    input  logic        start_of_packet, // Resets the calculation for a new packet
    input  logic [31:0] data_in,         // The input data
    
    output logic [31:0] crc_out,         // The result
    output logic        valid_out        // Tells the output interface the result is ready
);

    // The standard polynomial used for Ethernet
    localparam logic [31:0] POLYNOM  = 32'h04C11DB7;
    // CRC always starts with this value
    localparam logic [31:0] CRC_INIT = 32'hFFFFFFFF;

    // Internal signals used for the pipeline
    logic [31:0] data_in_pipe; 
    logic        enable_pipe;  
    logic        start_pipe;   
    
    // Registers for the CRC state
    logic [31:0] LFSR_Q;       // The current value
    logic [31:0] LFSR_NEXT;    // The next value we are calculating

    // Connect the internal registers to the outputs
    assign crc_out   = LFSR_Q;
    assign valid_out = enable_pipe; 

    // Save the inputs into registers to improve timing
    always_ff @(posedge clk or negedge reset_n) begin
        if (!reset_n) begin
            data_in_pipe <= 32'b0;
            enable_pipe  <= 1'b0;
            start_pipe   <= 1'b0;
        end else begin
            data_in_pipe <= data_in;
            enable_pipe  <= enable;
            start_pipe   <= start_of_packet;
        end
    end

    // Calculating the next CRC value
    always @(*) begin
        logic [31:0] current_state;

        // Select initial value or current state
        if (start_pipe) begin
            current_state = CRC_INIT; 
        end else begin
            current_state = LFSR_Q;   
        end

        LFSR_NEXT = current_state;

        // Loop for calculating all 32 bits in parallel
        for (int i = 0; i < 32; i++) begin
            // Check if the top bit matches
            if (LFSR_NEXT[31] ^ data_in_pipe[31-i]) begin
                 // Shift left and apply the polynomial
                 LFSR_NEXT = (LFSR_NEXT << 1) ^ POLYNOM;
            end else begin
                 // Shift left
                 LFSR_NEXT = (LFSR_NEXT << 1);
            end
        end
    end

    // Update the final register with the new result
    always_ff @(posedge clk or negedge reset_n) begin
        if (!reset_n) begin
            LFSR_Q <= CRC_INIT;
        end else if (enable_pipe) begin
            // Only update if we are enabled
            LFSR_Q <= LFSR_NEXT;
        end
    end

endmodule

tb_crc32.sv
/* Michael Mostytskyy 
 Project: CRC32 Ethernet Accelerator
 Description: 
    Self-checking testbench for the CRC32 module
    Verifies the design against Golden Vectors and performs Error Detection tests
*/

`timescale 1ns / 1ps

module tb_crc32;

    // Signals to connect to the module we are testing
    logic        clk;
    logic        reset_n;
    logic        enable;
    logic        start_of_packet;
    logic [31:0] data_in;
    logic [31:0] crc_out;
    logic        valid_out;

    // The correct CRC result we expect to see (Standard Ethernet value)
    localparam logic [31:0] GOLDEN_CRC = 32'hDF8A8A2B;

    // Generate the clock signal (flips every 5ns)
    initial begin
        clk = 0;
        forever #5 clk = ~clk;
    end

    // Create the waveform file to view in GTKWave
    initial begin
        $dumpfile("waves.vcd");
        $dumpvars(0, tb_crc32);
    end

    // Connect the testbench to the design
    CRC32_parallel_pipeline u_dut (
        .clk            (clk),
        .reset_n        (reset_n),
        .enable         (enable),
        .start_of_packet(start_of_packet),
        .data_in        (data_in),
        .crc_out        (crc_out),
        .valid_out      (valid_out)
    );

    // Main simulation block
    initial begin
        // Initialize all signals to zero
        reset_n = 0;
        enable  = 0;
        start_of_packet = 0;
        data_in = 0;
        
        #50;
        
        // Release the reset so the chip can start working
        @(posedge clk); 
        reset_n = 1;
        #20;

        // Send a dummy packet just to see if data flows correctly
        @(posedge clk);
        enable = 1;
        start_of_packet = 1;
        data_in = 32'h12345678;
        
        @(posedge clk);
        start_of_packet = 0;
        data_in = 32'h9ABCDEF0;
        
        @(posedge clk);
        enable = 0;
        data_in = 0;
        
        wait(valid_out == 1); // Wait for the result
        #40;
        
        // Test 1 -> Golden Vector Check
        // We send known data and check if the result matches the standard
        $display("\nTime: %0t |Test: golden vector check", $time);
        
        @(posedge clk);
        enable = 1;
        start_of_packet = 1;
        data_in = 32'h12345678;
        
        @(posedge clk);
        enable = 0;
        start_of_packet = 0;
        data_in = 0;
        
        wait(valid_out == 1);
        @(negedge clk);

        // Check if the output matches the expected Golden Value
        if (crc_out == GOLDEN_CRC) begin
            $display("\tPASS -> standard CRC32 verified!");
            $display("\tInput: 12345678 -> output: %h", crc_out);
        end else begin
            $display("\tFAIL -> expected: %h, got: %h", GOLDEN_CRC, crc_out);
        end

        #50;

        // Test 2 -> Error Detection Check
        // We send bad data (bit flip) and make sure the CRC changes
        $display("\nTime: %0t |Test: error detection check", $time);

        @(posedge clk);
        enable = 1;
        start_of_packet = 1;
        data_in = 32'h12345679; // Notice the 9 at the end  is error injected
        
        @(posedge clk);
        enable = 0;
        start_of_packet = 0;
        data_in = 0;
        
        wait(valid_out == 1);
        @(negedge clk);

        // The CRC should be different from the Golden one
        if (crc_out != GOLDEN_CRC) begin
            $display("\tPASS -> error detected successfully!");
            $display("\tCorrupted Input -> new CRC: %h (different from golden)", crc_out);
        end else begin
            $display("\tFAIL -> collision corrupted data produced same CRC.");
        end

        #50;
        $display("\nTime: %0t |all tests finished", $time);
        $finish; // Stop the simulation
    end

endmodule

waves.vcd
$date
	Sun Jan 11 14:38:53 2026
$end
$version
	Icarus Verilog
$end
$timescale
	1ps
$end
$scope module tb_crc32 $end
$var wire 1 ! valid_out $end
$var wire 32 " crc_out [31:0] $end
$var parameter 32 # GOLDEN_CRC $end
$var reg 1 $ clk $end
$var reg 32 % data_in [31:0] $end
$var reg 1 & enable $end
$var reg 1 ' reset_n $end
$var reg 1 ( start_of_packet $end
$scope module u_dut $end
$var wire 1 $ clk $end
$var wire 32 ) crc_out [31:0] $end
$var wire 32 * data_in [31:0] $end
$var wire 1 & enable $end
$var wire 1 ' reset_n $end
$var wire 1 ( start_of_packet $end
$var wire 1 ! valid_out $end
$var parameter 32 + CRC_INIT $end
$var parameter 32 , POLYNOM $end
$var reg 32 - LFSR_NEXT [31:0] $end
$var reg 32 . LFSR_Q [31:0] $end
$var reg 32 / data_in_pipe [31:0] $end
$var reg 1 0 enable_pipe $end
$var reg 1 1 start_pipe $end
$scope begin $unm_blk_11 $end
$var reg 32 2 current_state [31:0] $end
$scope begin $ivl_for_loop0 $end
$var integer 32 3 i [31:0] $end
$upscope $end
$upscope $end
$upscope $end
$upscope $end
$enddefinitions $end
$comment Show the parameter values. $end
$dumpall
b100110000010001110110110111 ,
b11111111111111111111111111111111 +
b11011111100010101000101000101011 #
$end
#0
$dumpvars
b100000 3
b11111111111111111111111111111111 2
01
00
b0 /
b11111111111111111111111111111111 .
b11000111000001001101110101111011 -
b0 *
b11111111111111111111111111111111 )
0(
0'
0&
b0 %
0$
b11111111111111111111111111111111 "
0!
$end
#5000
1$
#10000
0$
#15000
1$
#20000
0$
#25000
1$
#30000
0$
#35000
1$
#40000
0$
#45000
1$
#50000
0$
#55000
1'
1$
#60000
0$
#65000
1$
#70000
0$
#75000
b100000 3
b11011111100010101000101000101011 -
11
1!
10
b10010001101000101011001111000 /
b10010001101000101011001111000 %
b10010001101000101011001111000 *
1(
1&
1$
#80000
0$
#85000
b1111101001001001010001100011011 -
b100000 3
b11011111100010101000101000101011 2
b11011111100010101000101000101011 "
b11011111100010101000101000101011 )
b11011111100010101000101000101011 .
01
b10011010101111001101111011110000 /
b10011010101111001101111011110000 %
b10011010101111001101111011110000 *
0(
1$
#90000
0$
#95000
b11110011101010011011000111111 -
b100000 3
b1111101001001001010001100011011 2
0!
00
b0 /
b1111101001001001010001100011011 "
b1111101001001001010001100011011 )
b1111101001001001010001100011011 .
b0 %
b0 *
0&
1$
#100000
0$
#105000
1$
#110000
0$
#115000
1$
#120000
0$
#125000
1$
#130000
0$
#135000
b100000 3
b11011111100010101000101000101011 -
b11111111111111111111111111111111 2
11
1!
10
b10010001101000101011001111000 /
b10010001101000101011001111000 %
b10010001101000101011001111000 *
1(
1&
1$
#140000
0$
#145000
b10011111111101011110000001111000 -
b100000 3
b11011111100010101000101000101011 2
b11011111100010101000101000101011 "
b11011111100010101000101000101011 )
b11011111100010101000101000101011 .
01
0!
00
b0 /
b0 %
b0 *
0(
0&
1$
#150000
0$
#155000
1$
#160000
0$
#165000
1$
#170000
0$
#175000
1$
#180000
0$
#185000
1$
#190000
0$
#195000
1$
#200000
0$
#205000
b100000 3
b11011011010010111001011110011100 -
b11111111111111111111111111111111 2
11
1!
10
b10010001101000101011001111001 /
b10010001101000101011001111001 %
b10010001101000101011001111001 *
1(
1&
1$
#210000
0$
#215000
b11010110111110001000011111110101 -
b100000 3
b11011011010010111001011110011100 2
01
0!
00
b0 /
b11011011010010111001011110011100 "
b11011011010010111001011110011100 )
b11011011010010111001011110011100 .
b0 %
b0 *
0(
0&
1$
